GeoNite/GeoNite.py
GeoNite/__init__.py
GeoNite/common.py
GeoNite-0.0.1.dist-info/LICENSE
GeoNite-0.0.1.dist-info/METADATA
GeoNite-0.0.1.dist-info/WHEEL
GeoNite-0.0.1.dist-info/entry_points.txt
GeoNite-0.0.1.dist-info/top_level.txt
GeoNite-0.0.1.dist-info/RECORD
