Metadata-Version: 2.2
Name: GeoNite
Version: 0.0.1
Summary: Some_Night_Light_Visualization
Author-email: Martins Ugwu <martinsbuchie@gmail.com>
License: MIT License
Project-URL: Homepage, https://github.com/martinsbuchi2/GeoNite
Keywords: GeoNite
Classifier: Intended Audience :: Developers
Classifier: License :: OSI Approved :: MIT License
Classifier: Natural Language :: English
Classifier: Programming Language :: Python :: 3.8
Classifier: Programming Language :: Python :: 3.9
Classifier: Programming Language :: Python :: 3.10
Classifier: Programming Language :: Python :: 3.11
Classifier: Programming Language :: Python :: 3.12
Requires-Python: >=3.8
License-File: LICENSE
Requires-Dist: numpy
Provides-Extra: all
Requires-Dist: GeoNite[extra]; extra == "all"
Provides-Extra: extra
Requires-Dist: pandas; extra == "extra"
